toolstxf/__init__.py
toolstxf/algorithm.py
toolstxf-0.1.1.dist-info/licenses/LICENSE
toolstxf-0.1.1.dist-info/METADATA
toolstxf-0.1.1.dist-info/WHEEL
toolstxf-0.1.1.dist-info/top_level.txt
toolstxf-0.1.1.dist-info/RECORD
