Metadata-Version: 2.4
Name: toolstxf
Version: 0.1.1
Summary: 常用的一些包
Author-email: 大佬 <402066270@qq.com>
License: MIT
Keywords: example,demo
Classifier: Programming Language :: Python :: 3
Classifier: License :: OSI Approved :: MIT License
Classifier: Operating System :: OS Independent
License-File: LICENSE
Requires-Dist: numpy>=2.3.2
Dynamic: license-file
